scripts/__init__.py
scripts/elasticsearch_error_notifier.py
scripts/slack.py
robotmonitor-0.1.0.dist-info/LICENSE
robotmonitor-0.1.0.dist-info/METADATA
robotmonitor-0.1.0.dist-info/WHEEL
robotmonitor-0.1.0.dist-info/entry_points.txt
robotmonitor-0.1.0.dist-info/top_level.txt
robotmonitor-0.1.0.dist-info/RECORD
