Metadata-Version: 2.1
Name: robotmonitor
Version: 0.1.0
Summary: A tool to monitor and notify robot log errors.
Home-page: https://github.com/gorefbitim/robotmonitor
Author: Ofer Rahat
Author-email: leofer@gmail.com
Classifier: License :: OSI Approved :: GNU General Public License v3 (GPLv3)
Classifier: Operating System :: Microsoft :: Windows
Classifier: Operating System :: POSIX :: Linux
License-File: LICENSE
Requires-Dist: python-dotenv
Requires-Dist: requests
Requires-Dist: urllib3
